{
  "project_info": {
    "project_number": "89303939765",
    "project_id": "skycast-75641",
    "storage_bucket": "skycast-75641.appspot.com"
  },
  "client": [
    {
      "client_info": {
        "mobilesdk_app_id": "1:89303939765:android:d1c3984f73f09a7ad4dcfc",
        "android_client_info": {
          "package_name": "com.example.skycast"
        }
      },
      "oauth_client": [
        {
          "client_id": "89303939765-sbafnkmt7tbo4n52095vlbq94df9fl6b.apps.googleusercontent.com",
          "client_type": 3
        }
      ],
      "api_key": [
        {
          "current_key": "AIzaSyAKTVzqQPZEPdJiJ7X9chcbtNVn3q17FMs"
        }
      ],
      "services": {
        "appinvite_service": {
          "other_platform_oauth_client": [
            {
              "client_id": "89303939765-sbafnkmt7tbo4n52095vlbq94df9fl6b.apps.googleusercontent.com",
              "client_type": 3
            }
          ]
        }
      }
    }
  ],
  "configuration_version": "1"
}